LICENSE.txt
README.md
setup.py
Docassemble_Pattern.egg-info/PKG-INFO
Docassemble_Pattern.egg-info/SOURCES.txt
Docassemble_Pattern.egg-info/dependency_links.txt
Docassemble_Pattern.egg-info/not-zip-safe
Docassemble_Pattern.egg-info/requires.txt
Docassemble_Pattern.egg-info/top_level.txt
docassemble_pattern/__init__.py
docassemble_pattern/helpers.py
docassemble_pattern/text/__init__.py
docassemble_pattern/text/search.py
docassemble_pattern/text/tree.py
docassemble_pattern/text/de/__init__.py
docassemble_pattern/text/de/__main__.py
docassemble_pattern/text/de/de-context.txt
docassemble_pattern/text/de/de-frequency.txt
docassemble_pattern/text/de/de-lexicon.txt
docassemble_pattern/text/de/de-morphology.txt
docassemble_pattern/text/de/de-spelling.txt
docassemble_pattern/text/de/de-verbs.txt
docassemble_pattern/text/de/inflect.py
docassemble_pattern/text/en/__init__.py
docassemble_pattern/text/en/__main__.py
docassemble_pattern/text/en/en-context.txt
docassemble_pattern/text/en/en-entities.txt
docassemble_pattern/text/en/en-frequency.txt
docassemble_pattern/text/en/en-lexicon.txt
docassemble_pattern/text/en/en-model.slp
docassemble_pattern/text/en/en-morphology.txt
docassemble_pattern/text/en/en-sentiment.xml
docassemble_pattern/text/en/en-spelling.txt
docassemble_pattern/text/en/en-verbs.txt
docassemble_pattern/text/en/inflect.py
docassemble_pattern/text/en/inflect_quantify.py
docassemble_pattern/text/en/modality.py
docassemble_pattern/text/en/wordlist/__init__.py
docassemble_pattern/text/en/wordlist/academic.txt
docassemble_pattern/text/en/wordlist/basic.txt
docassemble_pattern/text/en/wordlist/profanity.txt
docassemble_pattern/text/en/wordlist/stopwords.txt
docassemble_pattern/text/en/wordlist/time.txt
docassemble_pattern/text/en/wordnet/__init__.py
docassemble_pattern/text/en/wordnet/resnik-ic2.txt
docassemble_pattern/text/en/wordnet/resnik-ic3.txt
docassemble_pattern/text/en/wordnet/dict/LICENSE.txt
docassemble_pattern/text/en/wordnet/dict/data.adj
docassemble_pattern/text/en/wordnet/dict/data.adv
docassemble_pattern/text/en/wordnet/dict/data.noun1
docassemble_pattern/text/en/wordnet/dict/data.noun2
docassemble_pattern/text/en/wordnet/dict/data.verb
docassemble_pattern/text/en/wordnet/dict/index.32
